data_collect/__init__.py
data_collect/client.py
data_collect/constants.py
data_collect/correlation_id.py
data_collect/logger.py
data_collect/queue.py
data_collect/setup.py
data_collect/thread.py
data_collect/utils.py
data_collect/data_types/__init__.py
data_collect/data_types/blob.py
data_collect/data_types/image.py
data_collect/data_types/text.py
endpoint/__init__.py
endpoint/setup.py
endpoint/endpoint_monitor/__init__.py
endpoint/endpoint_monitor/endpoint_monitor_client.py
endpoint/endpoint_monitor/getter.py
endpoint/endpointv1/__init__.py
endpoint/endpointv1/endpoint_api.py
endpoint/endpointv1/endpoint_api_deploy_job.py
endpoint/endpointv1/endpoint_api_deployment.py
endpoint/endpointv1/endpoint_api_endpoint_hub.py
endpoint/endpointv1/endpoint_client.py
tgi/__init__.py
tgi/client.py
tgi/locustfile.py
tgi/ui.py
tritonv2/__init__.py
tritonv2/bls_parser.py
tritonv2/client.py
tritonv2/client_factory.py
tritonv2/constants.py
tritonv2/dag_builder.py
tritonv2/ds_formatter.py
tritonv2/evaluator.py
tritonv2/exceptions.py
tritonv2/grpc_aio_client.py
tritonv2/grpc_client.py
tritonv2/grpc_interceptor.py
tritonv2/http_aio_client.py
tritonv2/http_client.py
tritonv2/model.py
tritonv2/model_config.py
tritonv2/module.py
tritonv2/python_bls_processor.py
tritonv2/setup.py
tritonv2/update_pbtxt.py
tritonv2/utils.py
tritonv2/server/__init__.py
tritonv2/server/config.py
tritonv2/server/const.py
tritonv2/server/local.py
tritonv2/server/server.py
vllm/__init__.py
vllm/client.py
vllm/client_openai.py
vllm/locustfile.py
vllm/ui.py
tritonv2-1.3.5.1.dist-info/METADATA
tritonv2-1.3.5.1.dist-info/WHEEL
tritonv2-1.3.5.1.dist-info/top_level.txt
tritonv2-1.3.5.1.dist-info/RECORD
