Metadata-Version: 2.1
Name: tritonv2
Version: 1.3.5.1
Summary: project descriptions here
Home-page: https://github.com/FlyTOmeLight
Author: zhoubohan
Author-email: zhoubohan.pro@gmail.com
License: MIT
Platform: UNKNOWN
Classifier: Programming Language :: Python
Classifier: Programming Language :: Python :: 3
Classifier: Programming Language :: Python :: 3.7
Classifier: Programming Language :: Python :: 3.8
Classifier: Programming Language :: Python :: 3.9
Requires-Python: >=3.7
Requires-Dist: numpy>=1.23.5
Requires-Dist: tenacity>=8.1.0
Requires-Dist: tritonclient[all]>=2.25.0
Requires-Dist: pydantic>=1.10.2
Requires-Dist: pyrate-limiter~=2.10.0
Requires-Dist: grpc-interceptor>=0.15.1
Requires-Dist: boto3
